lax_client/__init__.py
lax_client/circuit_breaker.py
lax_client/client.py
lax_client/exceptions.py
lax_client/message.py
lax_client/metrics.py
lax_client/options.py
lax_client/proto/__init__.py
lax_client/proto/broker_pb2.py
lax_client/proto/broker_pb2_grpc.py
lax_client/proto/streams_pb2.py
lax_client/proto/streams_pb2_grpc.py
lax_nats_client-0.2.4.dist-info/licenses/LICENSE
lax_nats_client-0.2.4.dist-info/METADATA
lax_nats_client-0.2.4.dist-info/WHEEL
lax_nats_client-0.2.4.dist-info/top_level.txt
lax_nats_client-0.2.4.dist-info/RECORD
