Metadata-Version: 2.4
Name: lax-nats-client
Version: 0.2.4
Summary: High-performance Python client for LAX NATS JetStream with smart routing
Home-page: https://gitlab.com/lambdax2/lambdax-development/lax-nats-jetstream
Author: Rahul Lamba
Author-email: Rahul Lamba <rahul2lamb@gmail.com>
License: MIT
Project-URL: Homepage, https://gitlab.com/lambdax2/lambdax-development/lax-nats-jetstream
Project-URL: Documentation, https://gitlab.com/lambdax2/lambdax-development/lax-nats-jetstream/-/blob/main/sdk/python/README.md
Project-URL: Repository, https://gitlab.com/lambdax2/lambdax-development/lax-nats-jetstream.git
Project-URL: Issues, https://gitlab.com/lambdax2/lambdax-development/lax-nats-jetstream/-/issues
Keywords: nats,jetstream,messaging,fastapi,async,microservices
Classifier: Development Status :: 4 - Beta
Classifier: Intended Audience :: Developers
Classifier: License :: OSI Approved :: MIT License
Classifier: Programming Language :: Python :: 3
Classifier: Programming Language :: Python :: 3.8
Classifier: Programming Language :: Python :: 3.9
Classifier: Programming Language :: Python :: 3.10
Classifier: Programming Language :: Python :: 3.11
Classifier: Programming Language :: Python :: 3.12
Classifier: Framework :: AsyncIO
Classifier: Framework :: FastAPI
Classifier: Topic :: Software Development :: Libraries :: Python Modules
Requires-Python: >=3.8
License-File: LICENSE
Requires-Dist: nats-py>=2.6.0
Requires-Dist: grpcio>=1.60.0
Requires-Dist: protobuf>=4.25.0
Requires-Dist: prometheus-client>=0.19.0
Requires-Dist: tenacity>=8.2.0
Provides-Extra: fastapi
Requires-Dist: fastapi>=0.104.0; extra == "fastapi"
Requires-Dist: uvicorn[standard]>=0.24.0; extra == "fastapi"
Provides-Extra: dev
Requires-Dist: pytest>=7.4.0; extra == "dev"
Requires-Dist: pytest-asyncio>=0.21.0; extra == "dev"
Requires-Dist: black>=23.0.0; extra == "dev"
Requires-Dist: mypy>=1.7.0; extra == "dev"
Requires-Dist: build>=0.10.0; extra == "dev"
Requires-Dist: twine>=4.0.0; extra == "dev"
Dynamic: author
Dynamic: home-page
Dynamic: license-file
Dynamic: requires-python
